arclet/letoderea/__init__.py
arclet/letoderea/breakpoint.py
arclet/letoderea/core.py
arclet/letoderea/decorate.py
arclet/letoderea/exceptions.py
arclet/letoderea/overload.py
arclet/letoderea/provider.py
arclet/letoderea/publisher.py
arclet/letoderea/py.typed
arclet/letoderea/ref.py
arclet/letoderea/scope.py
arclet/letoderea/scope.pyi
arclet/letoderea/subscriber.py
arclet/letoderea/typing.py
arclet_letoderea-0.20.1.dist-info/METADATA
arclet_letoderea-0.20.1.dist-info/WHEEL
arclet_letoderea-0.20.1.dist-info/entry_points.txt
arclet_letoderea-0.20.1.dist-info/licenses/LICENSE
arclet_letoderea-0.20.1.dist-info/RECORD
