Metadata-Version: 2.1
Name: arclet-letoderea
Version: 0.20.1
Summary: A high-performance, simple-structured event system, relies on asyncio
Keywords: asyncio,event-system,dispatch,dependency-injection
Author-Email: RF-Tar-Railt <rf_tar_railt@qq.com>
License: MIT
Classifier: Operating System :: OS Independent
Classifier: License :: OSI Approved :: MIT License
Classifier: Development Status :: 4 - Beta
Classifier: Typing :: Typed
Classifier: Programming Language :: Python :: 3.14
Classifier: Programming Language :: Python :: 3.13
Classifier: Programming Language :: Python :: 3.12
Classifier: Programming Language :: Python :: 3.11
Classifier: Programming Language :: Python :: 3.10
Project-URL: Repository, https://github.com/ArcletProject/Letoderea
Project-URL: Homepage, https://github.com/ArcletProject/Letoderea
Requires-Python: <4.0,>=3.10
Requires-Dist: tarina<0.8.0,>=0.7.0
Requires-Dist: typing-extensions>=4.12.0
